pixcat/__about__.py
pixcat/__init__.py
pixcat/__main__.py
pixcat/cli.py
pixcat/data.py
pixcat/image.py
pixcat/terminal.py
pixcat-0.1.4.dist-info/METADATA
pixcat-0.1.4.dist-info/RECORD
pixcat-0.1.4.dist-info/WHEEL
pixcat-0.1.4.dist-info/entry_points.txt
pixcat-0.1.4.dist-info/top_level.txt
