Metadata-Version: 2.1
Name: pixcat
Version: 0.1.4
Summary: Display images on a kitty terminal with optional resizing.
Home-page: https://github.com/mirukan/pixcat
Author: miruka
Author-email: miruka@disroot.org
License: LGPLv3
Keywords: kitty api cli terminal print display resize scale image picture graphic icat
Platform: UNKNOWN
Classifier: Development Status :: 3 - Alpha
Classifier: Intended Audience :: Developers
Classifier: Intended Audience :: End Users/Desktop
Classifier: Environment :: Console
Classifier: Topic :: Multimedia :: Graphics :: Viewers
Classifier: Topic :: Terminals
Classifier: License :: OSI Approved :: GNU Lesser General Public License v3 or later (LGPLv3+)
Classifier: Programming Language :: Python :: 3
Classifier: Programming Language :: Python :: 3 :: Only
Classifier: Programming Language :: Python :: 3.6
Classifier: Programming Language :: Python :: 3.7
Classifier: Natural Language :: English
Classifier: Operating System :: POSIX
Requires-Python: >=3.6, <4
Requires-Dist: blessed
Requires-Dist: docopt
Requires-Dist: pillow
Requires-Dist: requests
Requires-Dist: dataclasses; python_version < "3.7"
